gladiator/__init__.py
gladiator/checksums.py
gladiator/cli.py
gladiator/config.py
gladiator/arena/__init__.py
gladiator/arena/base.py
gladiator/arena/changes.py
gladiator/arena/items.py
lr_gladiator-0.25.0.dist-info/licenses/LICENSE
lr_gladiator-0.25.0.dist-info/METADATA
lr_gladiator-0.25.0.dist-info/WHEEL
lr_gladiator-0.25.0.dist-info/entry_points.txt
lr_gladiator-0.25.0.dist-info/top_level.txt
lr_gladiator-0.25.0.dist-info/RECORD
