Metadata-Version: 2.4
Name: lr-gladiator
Version: 0.25.0
Summary: CLI and Python client for Arena PLM (app.bom.com): login, get revisions, list/download attachments, and upload to working revisions.
Author-email: Jonas Estberger <jonas.estberger@lumenradio.com>
License: MIT
Keywords: Arena,PLM,BOM,attachments,CLI
Classifier: Programming Language :: Python :: 3
Classifier: License :: OSI Approved :: MIT License
Classifier: Operating System :: OS Independent
Requires-Python: >=3.9
License-File: LICENSE
Requires-Dist: requests>=2.32
Requires-Dist: typer>=0.12
Requires-Dist: rich>=13.7
Requires-Dist: pydantic>=2.8
Provides-Extra: dev
Requires-Dist: build>=1.2.1; extra == "dev"
Requires-Dist: twine>=5.1.1; extra == "dev"
Requires-Dist: wheel; extra == "dev"
Requires-Dist: pytest>=8.4.2; extra == "dev"
Requires-Dist: black>=25.9.0; extra == "dev"
Requires-Dist: pytest-html; extra == "dev"
Requires-Dist: pytest-cov; extra == "dev"
Dynamic: license-file
